pet_client_1_api_client/__init__.py
pet_client_1_api_client/api_client.py
pet_client_1_api_client/api_response.py
pet_client_1_api_client/configuration.py
pet_client_1_api_client/exceptions.py
pet_client_1_api_client/py.typed
pet_client_1_api_client/rest.py
pet_client_1_api_client/api/__init__.py
pet_client_1_api_client/api/pet_api.py
pet_client_1_api_client/api/store_api.py
pet_client_1_api_client/api/user_api.py
pet_client_1_api_client/models/__init__.py
pet_client_1_api_client/models/address.py
pet_client_1_api_client/models/api_response.py
pet_client_1_api_client/models/category.py
pet_client_1_api_client/models/customer.py
pet_client_1_api_client/models/order.py
pet_client_1_api_client/models/pet.py
pet_client_1_api_client/models/tag.py
pet_client_1_api_client/models/user.py
pet_client_1_api_client-1.0.0.dist-info/METADATA
pet_client_1_api_client-1.0.0.dist-info/WHEEL
pet_client_1_api_client-1.0.0.dist-info/top_level.txt
pet_client_1_api_client-1.0.0.dist-info/RECORD
